ardio/__init__.py
ardio/ardio.py
ardio-1.1.0.dist-info/entry_points.txt
ardio-1.1.0.dist-info/WHEEL
ardio-1.1.0.dist-info/METADATA
ardio-1.1.0.dist-info/RECORD
