Metadata-Version: 2.1
Name: ardio
Version: 1.1.0
Summary: Journal article to audio book
Home-page: https://github.com/dermatologist/ardio
Author: Bell Eapen
Author-email: github@gulfdoctor.net
Requires-Python: >=3.7,<4.0
Classifier: Development Status :: 4 - Beta
Classifier: Intended Audience :: Science/Research
Classifier: Operating System :: OS Independent
Classifier: Programming Language :: Python
Classifier: Programming Language :: Python :: 3
Classifier: Programming Language :: Python :: 3.7
Classifier: Programming Language :: Python :: 3.8
Classifier: Programming Language :: Python :: 3.9
Classifier: Topic :: Scientific/Engineering :: Information Analysis
Requires-Dist: gTTS (>=1.2.2,<2.0.0)
Requires-Dist: gTTS-token (>=1.1.4,<2.0.0)
Requires-Dist: pdfminer.six (>=20201018,<20201019)
Project-URL: Repository, https://github.com/dermatologist/ardio
